langchain_postgres/__init__.py
langchain_postgres/_utils.py
langchain_postgres/chat_message_histories.py
langchain_postgres/py.typed
langchain_postgres/translator.py
langchain_postgres/vectorstores.py
langchain_postgres/utils/pgvector_migrator.py
langchain_postgres/v2/__init__.py
langchain_postgres/v2/async_vectorstore.py
langchain_postgres/v2/engine.py
langchain_postgres/v2/hybrid_search_config.py
langchain_postgres/v2/indexes.py
langchain_postgres/v2/vectorstores.py
langchain_postgres_brim-0.0.15.dist-info/METADATA
langchain_postgres_brim-0.0.15.dist-info/WHEEL
langchain_postgres_brim-0.0.15.dist-info/licenses/LICENSE
langchain_postgres_brim-0.0.15.dist-info/RECORD
