Metadata-Version: 2.4
Name: langchain-postgres-brim
Version: 0.0.15
Summary: An integration package connecting Postgres and LangChain
License-Expression: MIT
License-File: LICENSE
Requires-Python: >=3.13
Requires-Dist: asyncpg>=0.30.0
Requires-Dist: langchain-core>=1.0.0a6
Requires-Dist: numpy<3,>=1.21
Requires-Dist: pgvector<0.4,>=0.2.5
Requires-Dist: psycopg-pool<4,>=3.2.1
Requires-Dist: psycopg<4,>=3
Requires-Dist: sqlalchemy<3,>=2
